models/__init__.py
models/accounts_chart.py
models/address.py
models/company.py
models/encoder.py
models/settings.py
models/transaction.py
pome/__init__.py
pome/_version.py
pome/currency.py
pome/misc.py
pome/routes.py
pome/test_routes.py
pome/models/__init__.py
pome/models/accounts_chart.py
pome/models/address.py
pome/models/bill.py
pome/models/company.py
pome/models/encoder.py
pome/models/invoice.py
pome/models/settings.py
pome/models/transaction.py
pome/models/transaction_filters.py
pome/models/validation.py
pome/static/.DS_Store
pome/static/bill.js
pome/static/download.svg
pome/static/git.svg
pome/static/global.css
pome/static/global.js
pome/static/invoice.js
pome/static/jquery.highlight-within-textarea.css
pome/static/jquery.highlight-within-textarea.js
pome/static/pome-round.png
pome/static/spinner.css
pome/static/tailwind.min.css
pome/static/transaction.js
pome/templates/account.html
pome/templates/base.html
pome/templates/bills.html
pome/templates/company.html
pome/templates/end-of-year.html
pome/templates/index.html
pome/templates/invoices.html
pome/templates/journal.html
pome/templates/metrics.html
pome/templates/new_bill.html
pome/templates/new_invoice.html
pome/templates/new_transaction.html
pome/templates/show_bill.html
pome/templates/show_invoice.html
pome/templates/show_transaction.html
pome-0.0.5.data/scripts/pome
pome-0.0.5.dist-info/LICENSE
pome-0.0.5.dist-info/METADATA
pome-0.0.5.dist-info/WHEEL
pome-0.0.5.dist-info/top_level.txt
pome-0.0.5.dist-info/RECORD
