Metadata-Version: 2.1
Name: pome
Version: 0.0.5
Summary: Distributed accounting software
Home-page: https://github.com/pome-gr/pome
Author: Tristan Stérin
Author-email: tristan@prgm.dev
License: UNKNOWN
Platform: UNKNOWN
Classifier: Programming Language :: Python :: 3
Classifier: License :: OSI Approved :: MIT License
Classifier: Operating System :: OS Independent
License-File: LICENSE
Requires-Dist: appdirs (==1.4.4)
Requires-Dist: Babel (==2.9.1)
Requires-Dist: black (==21.7b0)
Requires-Dist: certifi (==2021.5.30)
Requires-Dist: charset-normalizer (==2.0.4)
Requires-Dist: click (==8.0.1)
Requires-Dist: Flask (==2.0.1)
Requires-Dist: gitdb (==4.0.7)
Requires-Dist: GitPython (==3.1.18)
Requires-Dist: idna (==3.2)
Requires-Dist: isort (==5.9.3)
Requires-Dist: itsdangerous (==2.0.1)
Requires-Dist: Jinja2 (==3.0.1)
Requires-Dist: lorem-text (==1.5)
Requires-Dist: MarkupSafe (==2.0.1)
Requires-Dist: mypy-extensions (==0.4.3)
Requires-Dist: pathspec (==0.9.0)
Requires-Dist: pip-autoremove (==0.9.1)
Requires-Dist: py-money (==0.5.0)
Requires-Dist: pytz (==2021.1)
Requires-Dist: regex (==2021.8.3)
Requires-Dist: requests (==2.26.0)
Requires-Dist: smmap (==4.0.0)
Requires-Dist: tomli (==1.2.1)
Requires-Dist: urllib3 (==1.26.6)
Requires-Dist: Werkzeug (==2.0.1)
